postchain_client_py/__init__.py
postchain_client_py/blockchain_client/__init__.py
postchain_client_py/blockchain_client/blockchain_client.py
postchain_client_py/blockchain_client/crypto.py
postchain_client_py/blockchain_client/enums.py
postchain_client_py/blockchain_client/exceptions.py
postchain_client_py/blockchain_client/gtx.py
postchain_client_py/blockchain_client/interfaces.py
postchain_client_py/blockchain_client/transaction.py
postchain_client_py/blockchain_client/types.py
postchain_client_py/rest_client/__init__.py
postchain_client_py/rest_client/rest_client.py
postchain_client_py/utils/__init__.py
postchain_client_py/utils/formatters.py
postchain_client_py/utils/gtv.py
postchain_client_py/utils/gtv_hash.py
postchain_client_py/utils/logger.py
postchain_client_py/utils/types.py
postchain_client_py/utils/validation.py
postchain_client_py-0.2.3.dist-info/licenses/LICENSE
postchain_client_py-0.2.3.dist-info/METADATA
postchain_client_py-0.2.3.dist-info/WHEEL
postchain_client_py-0.2.3.dist-info/top_level.txt
postchain_client_py-0.2.3.dist-info/RECORD
