Metadata-Version: 2.4
Name: postchain_client_py
Version: 0.2.3
Summary: A Python client for Postchain
Author-email: TheCosmos <mert.akayasi@chromaway.com>
License: MIT License
Project-URL: Homepage, https://bitbucket.org/chromawallet/postchain-client-py
Keywords: blockchain,postchain,chromaway
Classifier: Programming Language :: Python :: 3
Classifier: License :: OSI Approved :: MIT License
Classifier: Operating System :: OS Independent
Requires-Python: >=3.7
License-File: LICENSE
Requires-Dist: aiohttp>=3.11.11
Requires-Dist: cryptography==44.0.0
Requires-Dist: ecdsa==0.19.0
Requires-Dist: coincurve==20.0.0
Requires-Dist: python-dotenv>=1.0.1
Requires-Dist: asn1==2.7.1
Provides-Extra: test
Requires-Dist: pytest>=7.0.0; extra == "test"
Requires-Dist: pytest-asyncio>=0.18.0; extra == "test"
Provides-Extra: dev
Requires-Dist: black>=22.0.0; extra == "dev"
Requires-Dist: wheel>=0.37.0; extra == "dev"
Requires-Dist: pytest>=7.0.0; extra == "dev"
Requires-Dist: pytest-asyncio>=0.18.0; extra == "dev"
Requires-Dist: rich>=13.0.0; extra == "dev"
Dynamic: license-file
